Workbook

Sheet Como usar
A1: Planilha financeira do casal — guia rápido
A3: Como preencher | B3: Edite só as células em AZUL. As colunas pretas são calculadas. Não mude os cabeçalhos.
A4: Abas de cada um | B4: 'Receitas Rodrigo' e 'Despesas Rodrigo' são do Rodrigo; 'Receitas Esposa' e 'Despesas Esposa' são dela. Cada um lança só o que é pessoal.
A5: Nome dela | B5: Para trocar 'Esposa' pelo nome dela: renomeie as duas abas ('Receitas Esposa' e 'Despesas Esposa') E o valor 'pessoa_2' na aba Premissas. As listas suspensas aceitam o nome novo (ou ajuste em Dados > Validação).
A6: Despesas Casal | B6: Gastos da casa (aluguel, energia, mercado…). A coluna 'Pago por' diz quem paga de fato; o painel calcula quanto cada um deveria pagar e quem deve transferir quanto.
A7: Divisão do casal | B7: Na aba Premissas: 'Proporcional à renda' (quem ganha mais paga mais), 'Igual (50/50)' ou 'Percentual fixo' (define a parte do pessoa_1).
A8: Frequência | B8: Mensal (todo mês entre Início e Fim; vazio = sempre), Anual (todo ano no mês do Início) ou Única (só no mês do Início).
A9: Reajusta? | B9: Receitas: 'Sim' aplica o reajuste salarial anual. Despesas: 'Sim' corrige pela inflação.
A10: Tipo (Despesas) | B10: Fixa ou Variável. Os cenários otimista/pessimista mexem só nas variáveis.
A11: De quem | B11: Em Parcelas, Investimentos e Lançamentos: Rodrigo, Esposa ou Casal (vazio = Casal).
A12: Cartões | B12: Cadastre os cartões na aba Cartões e marque na coluna 'Cartão' (Despesas e Parcelas) o que é cobrado em cada um. Vazio = Pix/débito/boleto. O painel monta a fatura de cada cartão.
A13: Lançamentos | B13: Opcional: o que realmente aconteceu. Alimenta o gráfico de histórico.
A14: Dados de exemplo | B14: Tudo que está preenchido é exemplo. Apague e coloque os seus valores.
A17: Resumo mensal (equivalente)
A18: Receita Rodrigo | B18: =SUM('Receitas Rodrigo'!H2:H1000) -> 10311.083
A19: Receita Esposa | B19: =SUM('Receitas Esposa'!H2:H1000) -> 6444.4167
A20: Despesas pessoais Rodrigo | B20: =SUM('Despesas Rodrigo'!I2:I1000) -> 1880
A21: Despesas pessoais Esposa | B21: =SUM('Despesas Esposa'!I2:I1000) -> 1665
A22: Despesas do casal | B22: =SUM('Despesas Casal'!J2:J1000) -> 5840
A23: Parcelas do mês | B23: =SUM(Parcelas!D2:D1000) -> 1050
A24: Aportes mensais | B24: =SUM(Investimentos!D2:D1000) -> 1600
A25: Sobra estimada da casa | B25: =B18+B19-B20-B21-B22-B23-B24 -> 4720.5
A27: Itens anuais entram como 1/12 por mês; itens únicos ficam fora deste resumo (o painel considera todos no mês certo).

Sheet Receitas Rodrigo
A1: Descrição | B1: Categoria | C1: Valor | D1: Frequência | E1: Início | F1: Fim | G1: Reajusta? | H1: Mensal equiv.
A2: Salário líquido | B2: Salário | C2: 8200 | D2: Mensal | G2: Sim | H2: =IF(C2="","",IF(D2="Mensal",C2,IF(D2="Anual",C2/12,0))) -> 8200
A3: Freela (contrato) | B3: Extra | C3: 1200 | D3: Mensal | F3: 46539 | G3: Não | H3: =IF(C3="","",IF(D3="Mensal",C3,IF(D3="Anual",C3/12,0))) -> 1200
A4: 13º salário | B4: Salário | C4: 8200 | D4: Anual | E4: 46357 | G4: Sim | H4: =IF(C4="","",IF(D4="Mensal",C4,IF(D4="Anual",C4/12,0))) -> 683.33333
A5: 1/3 de férias | B5: Salário | C5: 2733 | D5: Anual | E5: 46388 | G5: Sim | H5: =IF(C5="","",IF(D5="Mensal",C5,IF(D5="Anual",C5/12,0))) -> 227.75
A6: Restituição do IR | B6: Extra | C6: 1500 | D6: Única | E6: 46508 | G6: Não | H6: =IF(C6="","",IF(D6="Mensal",C6,IF(D6="Anual",C6/12,0))) -> 0
H7: =IF(C7="","",IF(D7="Mensal",C7,IF(D7="Anual",C7/12,0)))
H8: =IF(C8="","",IF(D8="Mensal",C8,IF(D8="Anual",C8/12,0)))
H9: =IF(C9="","",IF(D9="Mensal",C9,IF(D9="Anual",C9/12,0)))
H10: =IF(C10="","",IF(D10="Mensal",C10,IF(D10="Anual",C10/12,0)))
H11: =IF(C11="","",IF(D11="Mensal",C11,IF(D11="Anual",C11/12,0)))
H12: =IF(C12="","",IF(D12="Mensal",C12,IF(D12="Anual",C12/12,0)))
H13: =IF(C13="","",IF(D13="Mensal",C13,IF(D13="Anual",C13/12,0)))
H14: =IF(C14="","",IF(D14="Mensal",C14,IF(D14="Anual",C14/12,0)))
H15: =IF(C15="","",IF(D15="Mensal",C15,IF(D15="Anual",C15/12,0)))
H16: =IF(C16="","",IF(D16="Mensal",C16,IF(D16="Anual",C16/12,0)))
H17: =IF(C17="","",IF(D17="Mensal",C17,IF(D17="Anual",C17/12,0)))
H18: =IF(C18="","",IF(D18="Mensal",C18,IF(D18="Anual",C18/12,0)))
... H61: =IF(C61="","",IF(D61="Mensal",C61,IF(D61="Anual",C61/12,0)))

Sheet Receitas Esposa
A1: Descrição | B1: Categoria | C1: Valor | D1: Frequência | E1: Início | F1: Fim | G1: Reajusta? | H1: Mensal equiv.
A2: Salário líquido | B2: Salário | C2: 5800 | D2: Mensal | G2: Sim | H2: =IF(C2="","",IF(D2="Mensal",C2,IF(D2="Anual",C2/12,0))) -> 5800
A3: 13º salário | B3: Salário | C3: 5800 | D3: Anual | E3: 46357 | G3: Sim | H3: =IF(C3="","",IF(D3="Mensal",C3,IF(D3="Anual",C3/12,0))) -> 483.33333
A4: 1/3 de férias | B4: Salário | C4: 1933 | D4: Anual | E4: 46569 | G4: Sim | H4: =IF(C4="","",IF(D4="Mensal",C4,IF(D4="Anual",C4/12,0))) -> 161.08333
H5: =IF(C5="","",IF(D5="Mensal",C5,IF(D5="Anual",C5/12,0)))
H6: =IF(C6="","",IF(D6="Mensal",C6,IF(D6="Anual",C6/12,0)))
H7: =IF(C7="","",IF(D7="Mensal",C7,IF(D7="Anual",C7/12,0)))
H8: =IF(C8="","",IF(D8="Mensal",C8,IF(D8="Anual",C8/12,0)))
H9: =IF(C9="","",IF(D9="Mensal",C9,IF(D9="Anual",C9/12,0)))
H10: =IF(C10="","",IF(D10="Mensal",C10,IF(D10="Anual",C10/12,0)))
H11: =IF(C11="","",IF(D11="Mensal",C11,IF(D11="Anual",C11/12,0)))
H12: =IF(C12="","",IF(D12="Mensal",C12,IF(D12="Anual",C12/12,0)))
H13: =IF(C13="","",IF(D13="Mensal",C13,IF(D13="Anual",C13/12,0)))
H14: =IF(C14="","",IF(D14="Mensal",C14,IF(D14="Anual",C14/12,0)))
H15: =IF(C15="","",IF(D15="Mensal",C15,IF(D15="Anual",C15/12,0)))
H16: =IF(C16="","",IF(D16="Mensal",C16,IF(D16="Anual",C16/12,0)))
... H61: =IF(C61="","",IF(D61="Mensal",C61,IF(D61="Anual",C61/12,0)))

Sheet Despesas Rodrigo
A1: Descrição | B1: Categoria | C1: Tipo | D1: Valor | E1: Frequência | F1: Início | G1: Fim | H1: Reajusta? | I1: Mensal equiv. | J1: Cartão
A2: Celular | B2: Serviços | C2: Fixa | D2: 60 | E2: Mensal | H2: Não | I2: =IF(D2="","",IF(E2="Mensal",D2,IF(E2="Anual",D2/12,0))) -> 60 | J2: Nubank Rodrigo
A3: Plano de saúde | B3: Saúde | C3: Fixa | D3: 650 | E3: Mensal | H3: Sim | I3: =IF(D3="","",IF(E3="Mensal",D3,IF(E3="Anual",D3/12,0))) -> 650
A4: Academia | B4: Saúde | C4: Fixa | D4: 120 | E4: Mensal | H4: Sim | I4: =IF(D4="","",IF(E4="Mensal",D4,IF(E4="Anual",D4/12,0))) -> 120 | J4: Nubank Rodrigo
A5: Combustível | B5: Transporte | C5: Variável | D5: 450 | E5: Mensal | H5: Sim | I5: =IF(D5="","",IF(E5="Mensal",D5,IF(E5="Anual",D5/12,0))) -> 450 | J5: Nubank Rodrigo
A6: Lazer pessoal | B6: Lazer | C6: Variável | D6: 250 | E6: Mensal | H6: Sim | I6: =IF(D6="","",IF(E6="Mensal",D6,IF(E6="Anual",D6/12,0))) -> 250 | J6: Nubank Rodrigo
A7: Seguro do carro | B7: Transporte | C7: Fixa | D7: 2400 | E7: Anual | F7: 46447 | H7: Sim | I7: =IF(D7="","",IF(E7="Mensal",D7,IF(E7="Anual",D7/12,0))) -> 200
A8: IPVA | B8: Transporte | C8: Fixa | D8: 1800 | E8: Anual | F8: 46388 | H8: Sim | I8: =IF(D8="","",IF(E8="Mensal",D8,IF(E8="Anual",D8/12,0))) -> 150
I9: =IF(D9="","",IF(E9="Mensal",D9,IF(E9="Anual",D9/12,0)))
I10: =IF(D10="","",IF(E10="Mensal",D10,IF(E10="Anual",D10/12,0)))
I11: =IF(D11="","",IF(E11="Mensal",D11,IF(E11="Anual",D11/12,0)))
I12: =IF(D12="","",IF(E12="Mensal",D12,IF(E12="Anual",D12/12,0)))
I13: =IF(D13="","",IF(E13="Mensal",D13,IF(E13="Anual",D13/12,0)))
I14: =IF(D14="","",IF(E14="Mensal",D14,IF(E14="Anual",D14/12,0)))
I15: =IF(D15="","",IF(E15="Mensal",D15,IF(E15="Anual",D15/12,0)))
I16: =IF(D16="","",IF(E16="Mensal",D16,IF(E16="Anual",D16/12,0)))
I17: =IF(D17="","",IF(E17="Mensal",D17,IF(E17="Anual",D17/12,0)))
I18: =IF(D18="","",IF(E18="Mensal",D18,IF(E18="Anual",D18/12,0)))
I19: =IF(D19="","",IF(E19="Mensal",D19,IF(E19="Anual",D19/12,0)))
I20: =IF(D20="","",IF(E20="Mensal",D20,IF(E20="Anual",D20/12,0)))
... I61: =IF(D61="","",IF(E61="Mensal",D61,IF(E61="Anual",D61/12,0)))

Sheet Despesas Esposa
A1: Descrição | B1: Categoria | C1: Tipo | D1: Valor | E1: Frequência | F1: Início | G1: Fim | H1: Reajusta? | I1: Mensal equiv. | J1: Cartão
A2: Celular | B2: Serviços | C2: Fixa | D2: 55 | E2: Mensal | H2: Não | I2: =IF(D2="","",IF(E2="Mensal",D2,IF(E2="Anual",D2/12,0))) -> 55
A3: Plano de saúde | B3: Saúde | C3: Fixa | D3: 580 | E3: Mensal | H3: Sim | I3: =IF(D3="","",IF(E3="Mensal",D3,IF(E3="Anual",D3/12,0))) -> 580
A4: Pilates | B4: Saúde | C4: Fixa | D4: 280 | E4: Mensal | H4: Sim | I4: =IF(D4="","",IF(E4="Mensal",D4,IF(E4="Anual",D4/12,0))) -> 280 | J4: Itaú Esposa
A5: Transporte (app/ônibus) | B5: Transporte | C5: Variável | D5: 300 | E5: Mensal | H5: Sim | I5: =IF(D5="","",IF(E5="Mensal",D5,IF(E5="Anual",D5/12,0))) -> 300
A6: Cuidados pessoais | B6: Cuidados | C6: Variável | D6: 250 | E6: Mensal | H6: Sim | I6: =IF(D6="","",IF(E6="Mensal",D6,IF(E6="Anual",D6/12,0))) -> 250 | J6: Itaú Esposa
A7: Roupas | B7: Compras | C7: Variável | D7: 200 | E7: Mensal | H7: Sim | I7: =IF(D7="","",IF(E7="Mensal",D7,IF(E7="Anual",D7/12,0))) -> 200 | J7: Itaú Esposa
I8: =IF(D8="","",IF(E8="Mensal",D8,IF(E8="Anual",D8/12,0)))
I9: =IF(D9="","",IF(E9="Mensal",D9,IF(E9="Anual",D9/12,0)))
I10: =IF(D10="","",IF(E10="Mensal",D10,IF(E10="Anual",D10/12,0)))
I11: =IF(D11="","",IF(E11="Mensal",D11,IF(E11="Anual",D11/12,0)))
I12: =IF(D12="","",IF(E12="Mensal",D12,IF(E12="Anual",D12/12,0)))
I13: =IF(D13="","",IF(E13="Mensal",D13,IF(E13="Anual",D13/12,0)))
I14: =IF(D14="","",IF(E14="Mensal",D14,IF(E14="Anual",D14/12,0)))
I15: =IF(D15="","",IF(E15="Mensal",D15,IF(E15="Anual",D15/12,0)))
I16: =IF(D16="","",IF(E16="Mensal",D16,IF(E16="Anual",D16/12,0)))
I17: =IF(D17="","",IF(E17="Mensal",D17,IF(E17="Anual",D17/12,0)))
I18: =IF(D18="","",IF(E18="Mensal",D18,IF(E18="Anual",D18/12,0)))
I19: =IF(D19="","",IF(E19="Mensal",D19,IF(E19="Anual",D19/12,0)))
... I61: =IF(D61="","",IF(E61="Mensal",D61,IF(E61="Anual",D61/12,0)))

Sheet Despesas Casal
A1: Descrição | B1: Categoria | C1: Tipo | D1: Valor | E1: Frequência | F1: Início | G1: Fim | H1: Reajusta? | I1: Pago por | J1: Mensal equiv. | K1: Cartão
A2: Aluguel | B2: Moradia | C2: Fixa | D2: 2100 | E2: Mensal | H2: Sim | I2: Rodrigo | J2: =IF(D2="","",IF(E2="Mensal",D2,IF(E2="Anual",D2/12,0))) -> 2100
A3: Condomínio | B3: Moradia | C3: Fixa | D3: 480 | E3: Mensal | H3: Sim | I3: Esposa | J3: =IF(D3="","",IF(E3="Mensal",D3,IF(E3="Anual",D3/12,0))) -> 480
A4: Energia | B4: Moradia | C4: Variável | D4: 260 | E4: Mensal | H4: Sim | I4: Rodrigo | J4: =IF(D4="","",IF(E4="Mensal",D4,IF(E4="Anual",D4/12,0))) -> 260
A5: Água e gás | B5: Moradia | C5: Variável | D5: 140 | E5: Mensal | H5: Sim | I5: Esposa | J5: =IF(D5="","",IF(E5="Mensal",D5,IF(E5="Anual",D5/12,0))) -> 140
A6: Internet | B6: Moradia | C6: Fixa | D6: 120 | E6: Mensal | H6: Não | I6: Esposa | J6: =IF(D6="","",IF(E6="Mensal",D6,IF(E6="Anual",D6/12,0))) -> 120
A7: Mercado | B7: Alimentação | C7: Variável | D7: 1600 | E7: Mensal | H7: Sim | I7: Conta conjunta | J7: =IF(D7="","",IF(E7="Mensal",D7,IF(E7="Anual",D7/12,0))) -> 1600
A8: Restaurantes e delivery | B8: Alimentação | C8: Variável | D8: 650 | E8: Mensal | H8: Sim | I8: Rodrigo | J8: =IF(D8="","",IF(E8="Mensal",D8,IF(E8="Anual",D8/12,0))) -> 650 | K8: Nubank Rodrigo
A9: Streaming | B9: Lazer | C9: Fixa | D9: 90 | E9: Mensal | H9: Não | I9: Rodrigo | J9: =IF(D9="","",IF(E9="Mensal",D9,IF(E9="Anual",D9/12,0))) -> 90 | K9: Nubank Rodrigo
A10: Passeios juntos | B10: Lazer | C10: Variável | D10: 400 | E10: Mensal | H10: Sim | I10: Conta conjunta | J10: =IF(D10="","",IF(E10="Mensal",D10,IF(E10="Anual",D10/12,0))) -> 400
A11: Presentes de Natal | B11: Lazer | C11: Variável | D11: 1200 | E11: Única | F11: 46357 | H11: Não | I11: Conta conjunta | J11: =IF(D11="","",IF(E11="Mensal",D11,IF(E11="Anual",D11/12,0))) -> 0
A12: Viagem de férias | B12: Lazer | C12: Variável | D12: 6000 | E12: Única | F12: 46569 | H12: Não | I12: Conta conjunta | J12: =IF(D12="","",IF(E12="Mensal",D12,IF(E12="Anual",D12/12,0))) -> 0
J13: =IF(D13="","",IF(E13="Mensal",D13,IF(E13="Anual",D13/12,0)))
J14: =IF(D14="","",IF(E14="Mensal",D14,IF(E14="Anual",D14/12,0)))
J15: =IF(D15="","",IF(E15="Mensal",D15,IF(E15="Anual",D15/12,0)))
J16: =IF(D16="","",IF(E16="Mensal",D16,IF(E16="Anual",D16/12,0)))
J17: =IF(D17="","",IF(E17="Mensal",D17,IF(E17="Anual",D17/12,0)))
J18: =IF(D18="","",IF(E18="Mensal",D18,IF(E18="Anual",D18/12,0)))
J19: =IF(D19="","",IF(E19="Mensal",D19,IF(E19="Anual",D19/12,0)))
J20: =IF(D20="","",IF(E20="Mensal",D20,IF(E20="Anual",D20/12,0)))
J21: =IF(D21="","",IF(E21="Mensal",D21,IF(E21="Anual",D21/12,0)))
J22: =IF(D22="","",IF(E22="Mensal",D22,IF(E22="Anual",D22/12,0)))
J23: =IF(D23="","",IF(E23="Mensal",D23,IF(E23="Anual",D23/12,0)))
J24: =IF(D24="","",IF(E24="Mensal",D24,IF(E24="Anual",D24/12,0)))
... J61: =IF(D61="","",IF(E61="Mensal",D61,IF(E61="Anual",D61/12,0)))

Sheet Parcelas
A1: Descrição | B1: Categoria | C1: De quem | D1: Parcela | E1: Restantes | F1: Próxima | G1: Total restante | H1: Última parcela | I1: Cartão
A2: Notebook | B2: Compras | C2: Rodrigo | D2: 450 | E2: 7 | F2: 46331 | G2: =IF(D2="","",D2*E2) -> 3150 | H2: =IF(OR(F2="",E2=""),"",EDATE(F2,E2-1)) -> 46512 | I2: Nubank Rodrigo
A3: Geladeira | B3: Casa | C3: Casal | D3: 320 | E3: 3 | F3: 46336 | G3: =IF(D3="","",D3*E3) -> 960 | H3: =IF(OR(F3="",E3=""),"",EDATE(F3,E3-1)) -> 46397
A4: Curso de inglês | B4: Educação | C4: Esposa | D4: 280 | E4: 10 | F4: 46341 | G4: =IF(D4="","",D4*E4) -> 2800 | H4: =IF(OR(F4="",E4=""),"",EDATE(F4,E4-1)) -> 46614 | I4: Itaú Esposa
G5: =IF(D5="","",D5*E5) | H5: =IF(OR(F5="",E5=""),"",EDATE(F5,E5-1))
G6: =IF(D6="","",D6*E6) | H6: =IF(OR(F6="",E6=""),"",EDATE(F6,E6-1))
G7: =IF(D7="","",D7*E7) | H7: =IF(OR(F7="",E7=""),"",EDATE(F7,E7-1))
G8: =IF(D8="","",D8*E8) | H8: =IF(OR(F8="",E8=""),"",EDATE(F8,E8-1))
G9: =IF(D9="","",D9*E9) | H9: =IF(OR(F9="",E9=""),"",EDATE(F9,E9-1))
G10: =IF(D10="","",D10*E10) | H10: =IF(OR(F10="",E10=""),"",EDATE(F10,E10-1))
G11: =IF(D11="","",D11*E11) | H11: =IF(OR(F11="",E11=""),"",EDATE(F11,E11-1))
G12: =IF(D12="","",D12*E12) | H12: =IF(OR(F12="",E12=""),"",EDATE(F12,E12-1))
G13: =IF(D13="","",D13*E13) | H13: =IF(OR(F13="",E13=""),"",EDATE(F13,E13-1))
G14: =IF(D14="","",D14*E14) | H14: =IF(OR(F14="",E14=""),"",EDATE(F14,E14-1))
G15: =IF(D15="","",D15*E15) | H15: =IF(OR(F15="",E15=""),"",EDATE(F15,E15-1))
G16: =IF(D16="","",D16*E16) | H16: =IF(OR(F16="",E16=""),"",EDATE(F16,E16-1))
... G61: =IF(D61="","",D61*E61) | H61: =IF(OR(F61="",E61=""),"",EDATE(F61,E61-1))

Sheet Investimentos
A1: Descrição | B1: De quem | C1: Saldo atual | D1: Aporte mensal | E1: Rentabilidade anual
A2: Reserva de emergência | B2: Casal | C2: 15000 | D2: 1000 | E2: 0.1 | G2: Rentabilidades são exemplos: ajuste para o que você espera de cada aplicação.
A3: Longo prazo | B3: Rodrigo | C3: 8000 | D3: 300 | E3: 0.08
A4: Previdência | B4: Esposa | C4: 6000 | D4: 300 | E4: 0.08

Sheet Cartões
A1: Cartão | B1: De quem | C1: Fechamento (dia) | D1: Vencimento (dia) | E1: Limite | G1: Vazio na coluna 'Cartão' das despesas = Pix, débito ou boleto. No cartão, o gasto entra na fatura do mês seguinte.
A2: Nubank Rodrigo | B2: Rodrigo | C2: 3 | D2: 10 | E2: 8000
A3: Itaú Esposa | B3: Esposa | C3: 25 | D3: 5 | E3: 5000

Sheet Premissas
A1: Chave | B1: Parâmetro | C1: Valor | D1: Observação
A2: pessoa_1 | B2: Nome da pessoa 1 | C2: Rodrigo | D2: Igual ao final do nome das abas 'Receitas …' e 'Despesas …'.
A3: pessoa_2 | B3: Nome da pessoa 2 | C3: Esposa | D3: Troque pelo nome dela e renomeie as abas dela igual.
A4: divisao_casal | B4: Como dividir as despesas do casal | C4: Proporcional à renda | D4: Proporcional à renda / Igual (50/50) / Percentual fixo.
A5: percentual_pessoa_1 | B5: Parte da pessoa 1 (se Percentual fixo) | C5: 0.6 | D5: Só vale com 'Percentual fixo'. A pessoa 2 fica com o restante.
A6: saldo_conta | B6: Saldo em conta hoje (somando os dois) | C6: 4500 | D6: Dinheiro parado em conta corrente, fora dos investimentos.
A7: inflacao | B7: Inflação anual esperada | C7: 0.045 | D7: Exemplo. Corrige despesas com 'Reajusta? = Sim'.
A8: reajuste_salarial | B8: Reajuste salarial anual | C8: 0.05 | D8: Exemplo. Aplica nas receitas com 'Reajusta? = Sim'.
A9: mes_reajuste | B9: Mês do reajuste salarial (1 a 12) | C9: 5 | D9: Ex.: 5 = maio.
A10: meses_projecao | B10: Meses de projeção | C10: 24 | D10: Quantos meses à frente o painel projeta.
A11: meta_reserva_meses | B11: Meta de reserva (meses de despesa) | C11: 6 | D11: Indicador de reserva de emergência.
A12: otimista_variaveis | B12: Otimista: ajuste nas despesas variáveis | C12: -0.05 | D12: -5% = gastar 5% menos nas variáveis.
A13: otimista_inflacao | B13: Otimista: ajuste na inflação (p.p.) | C13: -0.01 | D13: -1 p.p. sobre a inflação esperada.
A14: pessimista_variaveis | B14: Pessimista: ajuste nas despesas variáveis | C14: 0.15 | D14: +15% nas variáveis.
A15: pessimista_inflacao | B15: Pessimista: ajuste na inflação (p.p.) | C15: 0.02 | D15: +2 p.p. sobre a inflação esperada.

Sheet Lançamentos
A1: Data | B1: Descrição | C1: Categoria | D1: De quem | E1: Tipo | F1: Valor
A2: 46144 | B2: Pilates | C2: Saúde | D2: Esposa | E2: Despesa | F2: 280
A3: 46144 | B3: Energia | C3: Moradia | D3: Casal | E3: Despesa | F3: 299.19
A4: 46144 | B4: Restaurantes e delivery | C4: Alimentação | D4: Casal | E4: Despesa | F4: 683.05
A5: 46144 | B5: Passeios juntos | C5: Lazer | D5: Casal | E5: Despesa | F5: 484.2
A6: 46145 | B6: Cuidados pessoais | C6: Cuidados | D6: Esposa | E6: Despesa | F6: 248.36
A7: 46145 | B7: Roupas | C7: Compras | D7: Esposa | E7: Despesa | F7: 183.25
A8: 46146 | B8: Água e gás | C8: Moradia | D8: Casal | E8: Despesa | F8: 167.86
A9: 46147 | B9: Salário líquido | C9: Salário | D9: Rodrigo | E9: Receita | F9: 8200
A10: 46147 | B10: Salário líquido | C10: Salário | D10: Esposa | E10: Receita | F10: 5800
A11: 46147 | B11: Plano de saúde | C11: Saúde | D11: Rodrigo | E11: Despesa | F11: 650
A12: 46147 | B12: Notebook (parcela) | C12: Compras | D12: Rodrigo | E12: Despesa | F12: 450
A13: 46152 | B13: Geladeira (parcela) | C13: Casa | D13: Casal | E13: Despesa | F13: 320
... A155: 46315 | B155: Celular | C155: Serviços | D155: Esposa | E155: Despesa | F155: 55
